odoo/addons/l10n_ch_adr_report/README.rst
odoo/addons/l10n_ch_adr_report/__init__.py
odoo/addons/l10n_ch_adr_report/__manifest__.py
odoo/addons/l10n_ch_adr_report/i18n/de.po
odoo/addons/l10n_ch_adr_report/i18n/fr.pot
odoo/addons/l10n_ch_adr_report/i18n/l10n_ch_adr_report.pot
odoo/addons/l10n_ch_adr_report/models/__init__.py
odoo/addons/l10n_ch_adr_report/models/product_product.py
odoo/addons/l10n_ch_adr_report/readme/AUTHORS.rst
odoo/addons/l10n_ch_adr_report/readme/CONTRIBUTORS.rst
odoo/addons/l10n_ch_adr_report/readme/CREDITS.rst
odoo/addons/l10n_ch_adr_report/readme/DESCRIPTION.rst
odoo/addons/l10n_ch_adr_report/report/DG_ch_delivery_report.xml
odoo/addons/l10n_ch_adr_report/report/__init__.py
odoo/addons/l10n_ch_adr_report/report/dangerous_delivery_report.py
odoo/addons/l10n_ch_adr_report/static/description/icon.png
odoo/addons/l10n_ch_adr_report/static/description/index.html
odoo/addons/l10n_ch_adr_report/static/src/scss/adr_report.scss
odoo/addons/l10n_ch_adr_report/views/assets.xml
odoo14_addon_l10n_ch_adr_report-14.0.1.0.1.dev7.dist-info/METADATA
odoo14_addon_l10n_ch_adr_report-14.0.1.0.1.dev7.dist-info/WHEEL
odoo14_addon_l10n_ch_adr_report-14.0.1.0.1.dev7.dist-info/top_level.txt
odoo14_addon_l10n_ch_adr_report-14.0.1.0.1.dev7.dist-info/RECORD
